{
  "generatedAt": "2026-05-15T23:38:24.376Z",
  "baseDate": "2026-05-17",
  "games": 6,
  "rangeStart": "2026-05-08",
  "rangeEnd": "2026-05-15",
  "foundGames": 6,
  "foundPitchingGames": 6,
  "mvp": {
    "name": "坂倉",
    "summary": "直近6試合 21打数5安打 .238 OPS.931 2本 3打点 4四球 6三振",
    "form": {
      "icon": "↑↑",
      "label": "絶好調",
      "level": 2,
      "cls": "form-hot2"
    }
  },
  "worst": {
    "name": "平川",
    "summary": "直近4試合 13打数1安打 .077 OPS.154 7三振",
    "form": {
      "icon": "↓↓",
      "label": "絶不調",
      "level": -2,
      "cls": "form-cold2"
    }
  },
  "pitcherMvp": {
    "name": "栗林",
    "summary": "直近1登板 9回 防御率0.00 自責0 被安1 奪三振9 1勝",
    "form": {
      "icon": "↑↑",
      "label": "絶好調",
      "level": 2,
      "cls": "form-hot2"
    }
  },
  "pitcherWorst": {
    "name": "岡本",
    "summary": "直近1登板 6回 防御率6.00 自責4 被安5 奪三振6 1敗",
    "form": {
      "icon": "↓↓",
      "label": "絶不調",
      "level": -2,
      "cls": "form-cold2"
    }
  },
  "players": [
    {
      "name": "坂倉",
      "games": 6,
      "ab": 21,
      "r": 3,
      "h": 5,
      "rbi": 3,
      "sb": 0,
      "hr": 2,
      "k": 6,
      "bb": 4,
      "double": 1,
      "triple": 0,
      "single": 2,
      "hbp": 0,
      "sf": 0,
      "avg": ".238",
      "avg_num": 0.238,
      "obp": ".360",
      "slg": ".571",
      "ops": ".931",
      "ops_num": 0.931,
      "form": {
        "icon": "↑↑",
        "label": "絶好調",
        "level": 2,
        "cls": "form-hot2"
      },
      "summary": "直近6試合 21打数5安打 .238 OPS.931 2本 3打点 4四球 6三振"
    },
    {
      "name": "モンテロ",
      "games": 6,
      "ab": 19,
      "r": 2,
      "h": 7,
      "rbi": 2,
      "sb": 0,
      "hr": 1,
      "k": 6,
      "bb": 0,
      "double": 0,
      "triple": 0,
      "single": 5,
      "hbp": 0,
      "sf": 0,
      "avg": ".368",
      "avg_num": 0.368,
      "obp": ".368",
      "slg": ".474",
      "ops": ".842",
      "ops_num": 0.842,
      "form": {
        "icon": "↑",
        "label": "好調",
        "level": 1,
        "cls": "form-hot1"
      },
      "summary": "直近6試合 19打数7安打 .368 OPS.842 1本 2打点 6三振"
    },
    {
      "name": "大盛",
      "games": 4,
      "ab": 17,
      "r": 4,
      "h": 5,
      "rbi": 1,
      "sb": 1,
      "hr": 1,
      "k": 1,
      "bb": 0,
      "double": 0,
      "triple": 0,
      "single": 4,
      "hbp": 0,
      "sf": 0,
      "avg": ".294",
      "avg_num": 0.294,
      "obp": ".294",
      "slg": ".471",
      "ops": ".765",
      "ops_num": 0.765,
      "form": {
        "icon": "↑",
        "label": "好調",
        "level": 1,
        "cls": "form-hot1"
      },
      "summary": "直近4試合 17打数5安打 .294 OPS.765 1本 1打点 1三振 1盗塁"
    },
    {
      "name": "辰見",
      "games": 4,
      "ab": 3,
      "r": 0,
      "h": 1,
      "rbi": 0,
      "sb": 3,
      "hr": 0,
      "k": 2,
      "bb": 0,
      "double": 0,
      "triple": 0,
      "single": 1,
      "hbp": 0,
      "sf": 0,
      "avg": ".333",
      "avg_num": 0.333,
      "obp": ".333",
      "slg": ".333",
      "ops": ".667",
      "ops_num": 0.667,
      "form": {
        "icon": "－",
        "label": "様子見",
        "level": 0,
        "cls": "form-none"
      },
      "summary": "直近4試合 3打数1安打 .333 OPS.667 2三振 3盗塁"
    },
    {
      "name": "勝田",
      "games": 5,
      "ab": 7,
      "r": 0,
      "h": 2,
      "rbi": 0,
      "sb": 0,
      "hr": 0,
      "k": 1,
      "bb": 2,
      "double": 0,
      "triple": 0,
      "single": 2,
      "hbp": 0,
      "sf": 0,
      "avg": ".286",
      "avg_num": 0.286,
      "obp": ".444",
      "slg": ".286",
      "ops": ".730",
      "ops_num": 0.73,
      "form": {
        "icon": "－",
        "label": "様子見",
        "level": 0,
        "cls": "form-none"
      },
      "summary": "直近5試合 7打数2安打 .286 OPS.730 2四球 1三振"
    },
    {
      "name": "菊池",
      "games": 5,
      "ab": 18,
      "r": 1,
      "h": 5,
      "rbi": 0,
      "sb": 0,
      "hr": 0,
      "k": 3,
      "bb": 3,
      "double": 0,
      "triple": 0,
      "single": 4,
      "hbp": 0,
      "sf": 0,
      "avg": ".278",
      "avg_num": 0.278,
      "obp": ".381",
      "slg": ".222",
      "ops": ".603",
      "ops_num": 0.603,
      "form": {
        "icon": "→",
        "label": "普通",
        "level": 0,
        "cls": "form-even"
      },
      "summary": "直近5試合 18打数5安打 .278 OPS.603 3四球 3三振"
    },
    {
      "name": "二俣",
      "games": 4,
      "ab": 12,
      "r": 0,
      "h": 3,
      "rbi": 2,
      "sb": 0,
      "hr": 0,
      "k": 2,
      "bb": 1,
      "double": 0,
      "triple": 0,
      "single": 3,
      "hbp": 1,
      "sf": 1,
      "avg": ".250",
      "avg_num": 0.25,
      "obp": ".333",
      "slg": ".250",
      "ops": ".583",
      "ops_num": 0.583,
      "form": {
        "icon": "→",
        "label": "普通",
        "level": 0,
        "cls": "form-even"
      },
      "summary": "直近4試合 12打数3安打 .250 OPS.583 2打点 1四球 2三振"
    },
    {
      "name": "矢野",
      "games": 5,
      "ab": 5,
      "r": 0,
      "h": 0,
      "rbi": 0,
      "sb": 0,
      "hr": 0,
      "k": 2,
      "bb": 1,
      "double": 0,
      "triple": 0,
      "single": 0,
      "hbp": 0,
      "sf": 0,
      "avg": ".000",
      "avg_num": 0,
      "obp": ".167",
      "slg": ".000",
      "ops": ".167",
      "ops_num": 0.167,
      "form": {
        "icon": "－",
        "label": "様子見",
        "level": 0,
        "cls": "form-none"
      },
      "summary": "直近5試合 5打数0安打 .000 OPS.167 1四球 2三振"
    },
    {
      "name": "前川",
      "games": 3,
      "ab": 3,
      "r": 0,
      "h": 0,
      "rbi": 0,
      "sb": 0,
      "hr": 0,
      "k": 0,
      "bb": 0,
      "double": 0,
      "triple": 0,
      "single": 0,
      "hbp": 0,
      "sf": 0,
      "avg": ".000",
      "avg_num": 0,
      "obp": ".000",
      "slg": ".000",
      "ops": ".000",
      "ops_num": 0,
      "form": {
        "icon": "－",
        "label": "様子見",
        "level": 0,
        "cls": "form-none"
      },
      "summary": "直近3試合 3打数0安打 .000 OPS.000"
    },
    {
      "name": "林",
      "games": 3,
      "ab": 2,
      "r": 0,
      "h": 0,
      "rbi": 0,
      "sb": 0,
      "hr": 0,
      "k": 0,
      "bb": 1,
      "double": 0,
      "triple": 0,
      "single": 0,
      "hbp": 0,
      "sf": 0,
      "avg": ".000",
      "avg_num": 0,
      "obp": ".333",
      "slg": ".000",
      "ops": ".333",
      "ops_num": 0.333,
      "form": {
        "icon": "－",
        "label": "様子見",
        "level": 0,
        "cls": "form-none"
      },
      "summary": "直近3試合 2打数0安打 .000 OPS.333 1四球"
    },
    {
      "name": "小園",
      "games": 6,
      "ab": 24,
      "r": 1,
      "h": 6,
      "rbi": 2,
      "sb": 1,
      "hr": 0,
      "k": 4,
      "bb": 2,
      "double": 0,
      "triple": 0,
      "single": 5,
      "hbp": 0,
      "sf": 0,
      "avg": ".250",
      "avg_num": 0.25,
      "obp": ".308",
      "slg": ".208",
      "ops": ".516",
      "ops_num": 0.516,
      "form": {
        "icon": "↓",
        "label": "不調",
        "level": -1,
        "cls": "form-cold1"
      },
      "summary": "直近6試合 24打数6安打 .250 OPS.516 2打点 2四球 4三振 1盗塁"
    },
    {
      "name": "持丸",
      "games": 6,
      "ab": 21,
      "r": 1,
      "h": 5,
      "rbi": 0,
      "sb": 0,
      "hr": 0,
      "k": 5,
      "bb": 1,
      "double": 1,
      "triple": 0,
      "single": 4,
      "hbp": 0,
      "sf": 0,
      "avg": ".238",
      "avg_num": 0.238,
      "obp": ".273",
      "slg": ".286",
      "ops": ".558",
      "ops_num": 0.558,
      "form": {
        "icon": "↓",
        "label": "不調",
        "level": -1,
        "cls": "form-cold1"
      },
      "summary": "直近6試合 21打数5安打 .238 OPS.558 1四球 5三振"
    },
    {
      "name": "田村",
      "games": 2,
      "ab": 8,
      "r": 0,
      "h": 1,
      "rbi": 1,
      "sb": 0,
      "hr": 0,
      "k": 1,
      "bb": 0,
      "double": 0,
      "triple": 0,
      "single": 1,
      "hbp": 0,
      "sf": 0,
      "avg": ".125",
      "avg_num": 0.125,
      "obp": ".125",
      "slg": ".125",
      "ops": ".250",
      "ops_num": 0.25,
      "form": {
        "icon": "↓",
        "label": "不調",
        "level": -1,
        "cls": "form-cold1"
      },
      "summary": "直近2試合 8打数1安打 .125 OPS.250 1打点 1三振"
    },
    {
      "name": "野間",
      "games": 3,
      "ab": 9,
      "r": 0,
      "h": 1,
      "rbi": 0,
      "sb": 0,
      "hr": 0,
      "k": 1,
      "bb": 0,
      "double": 0,
      "triple": 0,
      "single": 1,
      "hbp": 0,
      "sf": 0,
      "avg": ".111",
      "avg_num": 0.111,
      "obp": ".111",
      "slg": ".111",
      "ops": ".222",
      "ops_num": 0.222,
      "form": {
        "icon": "↓",
        "label": "不調",
        "level": -1,
        "cls": "form-cold1"
      },
      "summary": "直近3試合 9打数1安打 .111 OPS.222 1三振"
    },
    {
      "name": "秋山",
      "games": 3,
      "ab": 9,
      "r": 0,
      "h": 0,
      "rbi": 0,
      "sb": 0,
      "hr": 0,
      "k": 2,
      "bb": 0,
      "double": 0,
      "triple": 0,
      "single": 0,
      "hbp": 0,
      "sf": 0,
      "avg": ".000",
      "avg_num": 0,
      "obp": ".000",
      "slg": ".000",
      "ops": ".000",
      "ops_num": 0,
      "form": {
        "icon": "↓",
        "label": "不調",
        "level": -1,
        "cls": "form-cold1"
      },
      "summary": "直近3試合 9打数0安打 .000 OPS.000 2三振"
    },
    {
      "name": "平川",
      "games": 4,
      "ab": 13,
      "r": 0,
      "h": 1,
      "rbi": 0,
      "sb": 0,
      "hr": 0,
      "k": 7,
      "bb": 0,
      "double": 0,
      "triple": 0,
      "single": 1,
      "hbp": 0,
      "sf": 0,
      "avg": ".077",
      "avg_num": 0.077,
      "obp": ".077",
      "slg": ".077",
      "ops": ".154",
      "ops_num": 0.154,
      "form": {
        "icon": "↓↓",
        "label": "絶不調",
        "level": -2,
        "cls": "form-cold2"
      },
      "summary": "直近4試合 13打数1安打 .077 OPS.154 7三振"
    }
  ],
  "pitchers": [
    {
      "name": "栗林",
      "games": 1,
      "outs": 27,
      "ip": "9回",
      "er": 0,
      "r": 0,
      "h": 1,
      "hr": 0,
      "bb": 1,
      "k": 9,
      "pitches": 120,
      "win": 1,
      "loss": 0,
      "save": 0,
      "hold": 0,
      "era": 0,
      "form": {
        "icon": "↑↑",
        "label": "絶好調",
        "level": 2,
        "cls": "form-hot2"
      },
      "summary": "直近1登板 9回 防御率0.00 自責0 被安1 奪三振9 1勝"
    },
    {
      "name": "塹江",
      "games": 2,
      "outs": 9,
      "ip": "3回",
      "er": 0,
      "r": 0,
      "h": 0,
      "hr": 0,
      "bb": 1,
      "k": 3,
      "pitches": 33,
      "win": 1,
      "loss": 0,
      "save": 0,
      "hold": 0,
      "era": 0,
      "form": {
        "icon": "↑",
        "label": "好調",
        "level": 1,
        "cls": "form-hot1"
      },
      "summary": "直近2登板 3回 防御率0.00 自責0 被安0 奪三振3 1勝"
    },
    {
      "name": "ハーン",
      "games": 3,
      "outs": 9,
      "ip": "3回",
      "er": 0,
      "r": 0,
      "h": 0,
      "hr": 0,
      "bb": 1,
      "k": 4,
      "pitches": 48,
      "win": 0,
      "loss": 0,
      "save": 0,
      "hold": 2,
      "era": 0,
      "form": {
        "icon": "↑",
        "label": "好調",
        "level": 1,
        "cls": "form-hot1"
      },
      "summary": "直近3登板 3回 防御率0.00 自責0 被安0 奪三振4 2H"
    },
    {
      "name": "玉村",
      "games": 1,
      "outs": 18,
      "ip": "6回",
      "er": 1,
      "r": 1,
      "h": 5,
      "hr": 1,
      "bb": 1,
      "k": 4,
      "pitches": 79,
      "win": 0,
      "loss": 0,
      "save": 0,
      "hold": 0,
      "era": 1.5,
      "form": {
        "icon": "↑",
        "label": "好調",
        "level": 1,
        "cls": "form-hot1"
      },
      "summary": "直近1登板 6回 防御率1.50 自責1 被安5 奪三振4"
    },
    {
      "name": "辻",
      "games": 1,
      "outs": 3,
      "ip": "1回",
      "er": 0,
      "r": 0,
      "h": 0,
      "hr": 0,
      "bb": 0,
      "k": 2,
      "pitches": 11,
      "win": 0,
      "loss": 0,
      "save": 0,
      "hold": 0,
      "era": 0,
      "form": {
        "icon": "－",
        "label": "様子見",
        "level": 0,
        "cls": "form-none"
      },
      "summary": "直近1登板 1回 防御率0.00 自責0 被安0 奪三振2"
    },
    {
      "name": "益田",
      "games": 1,
      "outs": 3,
      "ip": "1回",
      "er": 0,
      "r": 0,
      "h": 1,
      "hr": 0,
      "bb": 0,
      "k": 0,
      "pitches": 15,
      "win": 0,
      "loss": 0,
      "save": 0,
      "hold": 0,
      "era": 0,
      "form": {
        "icon": "－",
        "label": "様子見",
        "level": 0,
        "cls": "form-none"
      },
      "summary": "直近1登板 1回 防御率0.00 自責0 被安1 奪三振0"
    },
    {
      "name": "常廣",
      "games": 1,
      "outs": 3,
      "ip": "1回",
      "er": 0,
      "r": 0,
      "h": 2,
      "hr": 0,
      "bb": 1,
      "k": 1,
      "pitches": 29,
      "win": 0,
      "loss": 0,
      "save": 0,
      "hold": 0,
      "era": 0,
      "form": {
        "icon": "－",
        "label": "様子見",
        "level": 0,
        "cls": "form-none"
      },
      "summary": "直近1登板 1回 防御率0.00 自責0 被安2 奪三振1"
    },
    {
      "name": "赤木",
      "games": 1,
      "outs": 6,
      "ip": "2回",
      "er": 0,
      "r": 0,
      "h": 1,
      "hr": 0,
      "bb": 0,
      "k": 1,
      "pitches": 21,
      "win": 0,
      "loss": 0,
      "save": 0,
      "hold": 0,
      "era": 0,
      "form": {
        "icon": "－",
        "label": "様子見",
        "level": 0,
        "cls": "form-none"
      },
      "summary": "直近1登板 2回 防御率0.00 自責0 被安1 奪三振1"
    },
    {
      "name": "森浦",
      "games": 2,
      "outs": 6,
      "ip": "2回",
      "er": 0,
      "r": 0,
      "h": 1,
      "hr": 0,
      "bb": 0,
      "k": 2,
      "pitches": 32,
      "win": 0,
      "loss": 0,
      "save": 0,
      "hold": 1,
      "era": 0,
      "form": {
        "icon": "－",
        "label": "様子見",
        "level": 0,
        "cls": "form-none"
      },
      "summary": "直近2登板 2回 防御率0.00 自責0 被安1 奪三振2 1H"
    },
    {
      "name": "髙",
      "games": 3,
      "outs": 7,
      "ip": "2回1/3",
      "er": 0,
      "r": 0,
      "h": 2,
      "hr": 0,
      "bb": 2,
      "k": 1,
      "pitches": 45,
      "win": 0,
      "loss": 0,
      "save": 0,
      "hold": 2,
      "era": 0,
      "form": {
        "icon": "－",
        "label": "様子見",
        "level": 0,
        "cls": "form-none"
      },
      "summary": "直近3登板 2回1/3 防御率0.00 自責0 被安2 奪三振1 2H"
    },
    {
      "name": "森下",
      "games": 1,
      "outs": 15,
      "ip": "5回",
      "er": 2,
      "r": 3,
      "h": 8,
      "hr": 0,
      "bb": 1,
      "k": 5,
      "pitches": 94,
      "win": 0,
      "loss": 1,
      "save": 0,
      "hold": 0,
      "era": 3.6,
      "form": {
        "icon": "→",
        "label": "普通",
        "level": 0,
        "cls": "form-even"
      },
      "summary": "直近1登板 5回 防御率3.60 自責2 被安8 奪三振5 1敗"
    },
    {
      "name": "鈴木",
      "games": 1,
      "outs": 3,
      "ip": "1回",
      "er": 1,
      "r": 1,
      "h": 2,
      "hr": 0,
      "bb": 0,
      "k": 0,
      "pitches": 24,
      "win": 0,
      "loss": 0,
      "save": 0,
      "hold": 0,
      "era": 9,
      "form": {
        "icon": "－",
        "label": "様子見",
        "level": 0,
        "cls": "form-none"
      },
      "summary": "直近1登板 1回 防御率9.00 自責1 被安2 奪三振0"
    },
    {
      "name": "中﨑",
      "games": 3,
      "outs": 6,
      "ip": "2回",
      "er": 2,
      "r": 2,
      "h": 2,
      "hr": 1,
      "bb": 1,
      "k": 2,
      "pitches": 39,
      "win": 0,
      "loss": 1,
      "save": 0,
      "hold": 1,
      "era": 9,
      "form": {
        "icon": "－",
        "label": "様子見",
        "level": 0,
        "cls": "form-none"
      },
      "summary": "直近3登板 2回 防御率9.00 自責2 被安2 奪三振2 1敗1H"
    },
    {
      "name": "床田",
      "games": 1,
      "outs": 20,
      "ip": "6回2/3",
      "er": 3,
      "r": 3,
      "h": 8,
      "hr": 1,
      "bb": 0,
      "k": 3,
      "pitches": 104,
      "win": 0,
      "loss": 0,
      "save": 0,
      "hold": 0,
      "era": 4.05,
      "form": {
        "icon": "↓",
        "label": "不調",
        "level": -1,
        "cls": "form-cold1"
      },
      "summary": "直近1登板 6回2/3 防御率4.05 自責3 被安8 奪三振3"
    },
    {
      "name": "遠藤",
      "games": 3,
      "outs": 13,
      "ip": "4回1/3",
      "er": 3,
      "r": 3,
      "h": 6,
      "hr": 1,
      "bb": 2,
      "k": 6,
      "pitches": 88,
      "win": 0,
      "loss": 1,
      "save": 0,
      "hold": 1,
      "era": 6.23,
      "form": {
        "icon": "↓",
        "label": "不調",
        "level": -1,
        "cls": "form-cold1"
      },
      "summary": "直近3登板 4回1/3 防御率6.23 自責3 被安6 奪三振6 1敗1H"
    },
    {
      "name": "岡本",
      "games": 1,
      "outs": 18,
      "ip": "6回",
      "er": 4,
      "r": 4,
      "h": 5,
      "hr": 1,
      "bb": 3,
      "k": 6,
      "pitches": 104,
      "win": 0,
      "loss": 1,
      "save": 0,
      "hold": 0,
      "era": 6,
      "form": {
        "icon": "↓↓",
        "label": "絶不調",
        "level": -2,
        "cls": "form-cold2"
      },
      "summary": "直近1登板 6回 防御率6.00 自責4 被安5 奪三振6 1敗"
    }
  ]
}
